src/__init__.py
src/main.py
src/ieca/__init__.py
src/ieca/actividad.py
src/ieca/consulta.py
src/ieca/datos.py
src/ieca/jerarquia.py
src/utiles/__init__.py
src/utiles/embellecedor_metadatos.py
src/utiles/traducir.py
src/utiles/validador.py
src/utiles/metadatos/__init__.py
IECA_extractor-1.2.0.dist-info/METADATA
IECA_extractor-1.2.0.dist-info/WHEEL
IECA_extractor-1.2.0.dist-info/top_level.txt
IECA_extractor-1.2.0.dist-info/RECORD
